qdvis/__init__.py
qdvis/cli.py
qdvis/manage.py
qdvis/writer.py
qdvis/api/__init__.py
qdvis/api/admin.py
qdvis/api/apps.py
qdvis/api/models.py
qdvis/api/serializers.py
qdvis/api/tests.py
qdvis/api/urls.py
qdvis/api/views.py
qdvis/api/migrations/__init__.py
qdvis/config/__init__.py
qdvis/config/asgi.py
qdvis/config/settings.py
qdvis/config/urls.py
qdvis/config/wsgi.py
qdvis/vue_dist/favicon.ico
qdvis/vue_dist/index.html
qdvis/vue_dist/css/app.8e58ff9c.css
qdvis/vue_dist/js/app.25031460.js
qdvis/vue_dist/js/app.25031460.js.map
qdvis/vue_dist/js/chunk-vendors.b007b008.js
qdvis/vue_dist/js/chunk-vendors.b007b008.js.map
qdvis-0.1.2.dist-info/LICENSE
qdvis-0.1.2.dist-info/METADATA
qdvis-0.1.2.dist-info/WHEEL
qdvis-0.1.2.dist-info/entry_points.txt
qdvis-0.1.2.dist-info/top_level.txt
qdvis-0.1.2.dist-info/RECORD
