Metadata-Version: 2.1
Name: qdvis
Version: 0.1.2
Summary: qdvis: Quick data visualizer.
Home-page: https://github.com/ta-ke-inf/qdvis/tree/main
Download-URL: https://github.com/ta-ke-inf/qdvis/tree/main
Author: Takeguchi
Author-email: hirotake.stu@gmail.com
Maintainer: Takeguchi
Maintainer-email: hirotake.stu@gmail.com
License: MIT
Keywords: visualization ml
License-File: LICENSE
Requires-Dist: djangorestframework >=3.14.0
Requires-Dist: wheel >=0.42.0
